cb2game/__init__.py
cb2game/deploy.py
cb2game/agents/__init__.py
cb2game/agents/agent.py
cb2game/agents/config.py
cb2game/agents/create_agent.py
cb2game/agents/generate_config.py
cb2game/agents/gpt_follower.py
cb2game/agents/gpt_follower_example.yaml
cb2game/agents/local_agent_pair.py
cb2game/agents/remote_agent.py
cb2game/agents/simple_follower.py
cb2game/agents/simple_follower.yaml
cb2game/agents/simple_leader.py
cb2game/agents/test_local_agent_pair.py
cb2game/envs/cb2.py
cb2game/envs/demo_self_play.py
cb2game/eval/README.md
cb2game/eval/__init__.py
cb2game/eval/eval_schema.py
cb2game/eval/run_eval.py
cb2game/eval/visualize_eval.py
cb2game/follower_bots/README.md
cb2game/follower_bots/constants.py
cb2game/follower_bots/utils.py
cb2game/follower_bots/data_configs/pretraining_examples.json
cb2game/follower_bots/data_utils/data_classes.py
cb2game/follower_bots/data_utils/preprocess_sql.py
cb2game/follower_bots/data_utils/pyclient_utils.py
cb2game/follower_bots/data_utils/sql_dataset.py
cb2game/follower_bots/models/ensembled_models.py
cb2game/follower_bots/models/follower_transformers.py
cb2game/follower_bots/models/hex_conv.py
cb2game/follower_bots/models/hex_util.py
cb2game/follower_bots/models/model_utils.py
cb2game/follower_bots/models/pose.py
cb2game/follower_bots/models/rotation.py
cb2game/follower_bots/training/evaluate_pretrained_on_corpora.py
cb2game/follower_bots/training/follower_demo.py
cb2game/follower_bots/training/pretrain_follower.py
cb2game/follower_bots/training/train_utils.py
cb2game/follower_bots/training/scripts/run_1.sh
cb2game/follower_bots/training/scripts/run_2.sh
cb2game/follower_bots/training/scripts/run_3.sh
cb2game/pyclient/README.md
cb2game/pyclient/__init__.py
cb2game/pyclient/client_messages.py
cb2game/pyclient/client_utils.py
cb2game/pyclient/endpoint_pair.py
cb2game/pyclient/follower_data_masking.py
cb2game/pyclient/game_endpoint.py
cb2game/pyclient/game_socket.py
cb2game/pyclient/local_game_coordinator.py
cb2game-1.0.3.dist-info/METADATA
cb2game-1.0.3.dist-info/WHEEL
cb2game-1.0.3.dist-info/licenses/LICENSE.md
cb2game-1.0.3.dist-info/RECORD
