Metadata-Version: 2.1
Name: cb2game
Version: 1.0.3
Summary: A Collaborative Natural Language Instruction Game
Project-URL: Homepage, https://cb2.ai/
Project-URL: Bug Tracker, https://github.com/lil-lab/cb2/issues
Author-email: Jacob Sharf <jacobsharf@gmail.com>, Mustafa Omer Gul <momergul@gmail.com>, Yoav Artzi <yoav@cs.cornell.edu>
License-File: LICENSE.md
Classifier: License :: OSI Approved :: MIT License
Classifier: Operating System :: OS Independent
Classifier: Programming Language :: Python :: 3
Requires-Python: >=3.8
Requires-Dist: aiohttp-session==2.12.0
Requires-Dist: aiohttp-session[secure]==2.12.0
Requires-Dist: aiohttp==3.8.4
Requires-Dist: appdirs==1.4.4
Requires-Dist: autoflake==1.7.7
Requires-Dist: blessed==1.20.0
Requires-Dist: cachecontrol==0.12.11
Requires-Dist: colorhash==1.1.0
Requires-Dist: cryptography==41.0.1
Requires-Dist: dataclasses-json==0.5.6
Requires-Dist: fire==0.4.0
Requires-Dist: freetype-py==2.2.0
Requires-Dist: gitpython==3.1.31
Requires-Dist: google-auth==2.14.0
Requires-Dist: gymnasium==0.26.3
Requires-Dist: humanhash3==0.0.6
Requires-Dist: mashumaro==3.5
Requires-Dist: matplotlib==3.5.1
Requires-Dist: nest-asyncio==1.5.6
Requires-Dist: numpy==1.23.5
Requires-Dist: openai==0.27.2
Requires-Dist: orjson==3.6.7
Requires-Dist: pandas==2.0.3
Requires-Dist: pdoc==13.1.1
Requires-Dist: peewee==3.14.8
Requires-Dist: pendulum==2.1.2
Requires-Dist: pre-commit==2.20.0
Requires-Dist: pygame==2.1.2
Requires-Dist: pylint==2.15.5
Requires-Dist: python-dateutil==2.8.2
Requires-Dist: pyyaml==6.0
Requires-Dist: requests==2.28.1
Requires-Dist: sparklines==0.4.2
Requires-Dist: tiktoken==0.4.0
Requires-Dist: time-machine==2.8.2
Requires-Dist: tqdm==4.64.0
Requires-Dist: viztracer==0.15.6
Requires-Dist: watchdog==3.0.0
